dsns/__init__.py
dsns/constellation.py
dsns/events.py
dsns/helpers.py
dsns/logging.py
dsns/message.py
dsns/message_actors.py
dsns/multiconstellation.py
dsns/presets.py
dsns/reference_scenarios.py
dsns/simulation.py
dsns/traffic_sim.py
dsns/transmission.py
dsns/visualizer.py
dsns-1.0.0.dist-info/licenses/LICENSE
dsns-1.0.0.dist-info/METADATA
dsns-1.0.0.dist-info/WHEEL
dsns-1.0.0.dist-info/top_level.txt
dsns-1.0.0.dist-info/RECORD
