Metadata-Version: 2.4
Name: dsns
Version: 1.0.0
Summary: An event-based network simulator optimized for federated and deep-space satellite networks.
Author-email: Joshua Smailes <joshua.smailes@cs.ox.ac.uk>
License-Expression: GPL-3.0-or-later
Project-URL: Homepage, https://github.com/ssloxford/dsns
Project-URL: Issues, https://github.com/ssloxford/dsns/issues
Classifier: Programming Language :: Python :: 3
Classifier: Operating System :: OS Independent
Classifier: Development Status :: 5 - Production/Stable
Requires-Python: >=3.11
License-File: LICENSE
Requires-Dist: sphinx
Requires-Dist: sphinx-argparse
Requires-Dist: sphinx-rtd-theme
Requires-Dist: PyAstronomy
Requires-Dist: sgp4
Requires-Dist: pyrender; python_version <= "0.1.45"
Requires-Dist: networkit
Requires-Dist: pyrender
Requires-Dist: numpy
Requires-Dist: pandas
Requires-Dist: tqdm
Dynamic: license-file
